LICENSE
ansiblelater/__init__.py
ansiblelater/__main__.py
ansiblelater/candidate.py
ansiblelater/exceptions.py
ansiblelater/logger.py
ansiblelater/rule.py
ansiblelater/rules/CheckBecomeUser.py
ansiblelater/rules/CheckBracesSpaces.py
ansiblelater/rules/CheckChangedInWhen.py
ansiblelater/rules/CheckCommandHasChanges.py
ansiblelater/rules/CheckCommandInsteadOfArgument.py
ansiblelater/rules/CheckCommandInsteadOfModule.py
ansiblelater/rules/CheckCompareToEmptyString.py
ansiblelater/rules/CheckCompareToLiteralBool.py
ansiblelater/rules/CheckDeprecated.py
ansiblelater/rules/CheckDeprecatedBareVars.py
ansiblelater/rules/CheckFQCNBuiltin.py
ansiblelater/rules/CheckFilePermissionMissing.py
ansiblelater/rules/CheckFilePermissionOctal.py
ansiblelater/rules/CheckFilterSeparation.py
ansiblelater/rules/CheckGitHasVersion.py
ansiblelater/rules/CheckInstallUseLatest.py
ansiblelater/rules/CheckKeyOrder.py
ansiblelater/rules/CheckLiteralBoolFormat.py
ansiblelater/rules/CheckLocalAction.py
ansiblelater/rules/CheckMetaChangeFromDefault.py
ansiblelater/rules/CheckMetaMain.py
ansiblelater/rules/CheckNameFormat.py
ansiblelater/rules/CheckNamedTask.py
ansiblelater/rules/CheckNativeYaml.py
ansiblelater/rules/CheckNestedJinja.py
ansiblelater/rules/CheckRelativeRolePaths.py
ansiblelater/rules/CheckScmInSrc.py
ansiblelater/rules/CheckShellInsteadCommand.py
ansiblelater/rules/CheckTaskSeparation.py
ansiblelater/rules/CheckUniqueNamedTask.py
ansiblelater/rules/CheckWhenFormat.py
ansiblelater/rules/CheckYamlColons.py
ansiblelater/rules/CheckYamlDocumentEnd.py
ansiblelater/rules/CheckYamlDocumentStart.py
ansiblelater/rules/CheckYamlEmptyLines.py
ansiblelater/rules/CheckYamlFile.py
ansiblelater/rules/CheckYamlHasContent.py
ansiblelater/rules/CheckYamlHyphens.py
ansiblelater/rules/CheckYamlIndent.py
ansiblelater/rules/CheckYamlOctalValues.py
ansiblelater/settings.py
ansiblelater/test/__init__.py
ansiblelater/test/unit/__init__.py
ansiblelater/test/unit/test_logger.py
ansible_later-4.0.8.dist-info/LICENSE
ansible_later-4.0.8.dist-info/METADATA
ansible_later-4.0.8.dist-info/WHEEL
ansible_later-4.0.8.dist-info/entry_points.txt
ansible_later-4.0.8.dist-info/RECORD
