Metadata-Version: 2.1
Name: ansible-later
Version: 4.0.8
Summary: Reviews ansible playbooks, roles and inventories and suggests improvements.
Home-page: https://ansible-later.geekdocs.de/
License: MIT
Keywords: ansible,code,review
Author: Robert Kaussow
Author-email: mail@thegeeklab.de
Requires-Python: >=3.9.0,<4.0.0
Classifier: Development Status :: 5 - Production/Stable
Classifier: Environment :: Console
Classifier: Intended Audience :: Developers
Classifier: Intended Audience :: Information Technology
Classifier: Intended Audience :: System Administrators
Classifier: License :: OSI Approved :: MIT License
Classifier: Natural Language :: English
Classifier: Operating System :: POSIX
Classifier: Programming Language :: Python :: 3
Classifier: Programming Language :: Python :: 3.9
Classifier: Programming Language :: Python :: 3.10
Classifier: Programming Language :: Python :: 3.11
Classifier: Programming Language :: Python :: 3.12
Classifier: Programming Language :: Python :: 3.13
Classifier: Topic :: Software Development
Classifier: Topic :: Utilities
Provides-Extra: ansible
Provides-Extra: ansible-core
Requires-Dist: PyYAML (==6.0.2)
Requires-Dist: ansible (==7.7.0) ; extra == "ansible"
Requires-Dist: ansible-core (==2.14.17) ; extra == "ansible-core"
Requires-Dist: anyconfig (==0.14.0)
Requires-Dist: appdirs (==1.4.4)
Requires-Dist: colorama (==0.4.6)
Requires-Dist: jsonschema (==4.23.0)
Requires-Dist: nested-lookup (==0.2.25)
Requires-Dist: pathspec (==0.12.1)
Requires-Dist: python-json-logger (==2.0.7)
Requires-Dist: toolz (==1.0.0)
Requires-Dist: unidiff (==0.7.5)
Requires-Dist: yamllint (==1.35.1)
Project-URL: Documentation, https://ansible-later.geekdocs.de/
Project-URL: Repository, https://github.com/thegeeklab/ansible-later/
